__init__.py
precision_rounding.py
precision_rounding-0.1.dist-info/LICENSE
precision_rounding-0.1.dist-info/METADATA
precision_rounding-0.1.dist-info/WHEEL
precision_rounding-0.1.dist-info/top_level.txt
precision_rounding-0.1.dist-info/RECORD
